<!-- Indices written at Fri, 19 Apr 2013 17:33:42 EDT -->

<datastore-indexes autoGenerate="true">

    <!-- Used 1 time in query history -->
    <datastore-index kind="TTTGame" ancestor="false" source="auto">
        <property name="isAccepted" direction="asc"/>
        <property name="isActive" direction="asc"/>
        <property name="user1" direction="asc"/>
        <property name="winner" direction="asc"/>
        <property name="__key__" direction="desc"/>
    </datastore-index>

    <!-- Used 1 time in query history -->
    <datastore-index kind="TTTGame" ancestor="false" source="auto">
        <property name="isAccepted" direction="asc"/>
        <property name="isActive" direction="asc"/>
        <property name="user2" direction="asc"/>
        <property name="winner" direction="asc"/>
        <property name="__key__" direction="desc"/>
    </datastore-index>
    
    <datastore-index kind="TTTGame" ancestor="false" source="manual">
        <property name="isAccepted" direction="asc"/>
        <property name="isActive" direction="asc"/>
        <property name="user2" direction="asc"/>
        <property name="__key__" direction="desc"/>
    </datastore-index>

</datastore-indexes>
